example/click_options.py
example/decorator.py
example/dict.py
example/entry_points.py
example/git_examples.py
example/logging_examples.py
example/misc_python.py
example/docker/docker_examples.py
setupservers/__init__.py
setupservers/commands.py
setupservers/states.py
setupservers/util.py
setupservers/__pycache__/__init__.cpython-38.pyc
setupservers/__pycache__/__init__.cpython-39.pyc
setupservers/__pycache__/commands.cpython-38.pyc
setupservers/__pycache__/states.cpython-38.pyc
setupservers/__pycache__/util.cpython-38.pyc
setupservers/command/__init__.py
setupservers/command/hapi_jpa_starter.py
setupservers/command/init.py
setupservers/command/postgres_docker.py
setupservers/command/__pycache__/__init__.cpython-38.pyc
setupservers/command/__pycache__/__init__.cpython-39.pyc
setupservers/command/__pycache__/hapi_jpa_starter.cpython-38.pyc
setupservers/command/__pycache__/init.cpython-38.pyc
setupservers/command/__pycache__/postgres_docker.cpython-38.pyc
setup_servers-0.1.13.dist-info/METADATA
setup_servers-0.1.13.dist-info/WHEEL
setup_servers-0.1.13.dist-info/entry_points.txt
setup_servers-0.1.13.dist-info/top_level.txt
setup_servers-0.1.13.dist-info/RECORD
