Metadata-Version: 2.1
Name: setup-servers
Version: 0.1.13
Author: Shahim Essaid
Classifier: Programming Language :: Python :: 3
Classifier: License :: OSI Approved :: MIT License
Classifier: Operating System :: OS Independent
Requires-Python: >=3.8
Requires-Dist: stevedore
Requires-Dist: clickactions (==0.1.1)
Requires-Dist: filelock
Requires-Dist: pyyaml
Requires-Dist: docker
Requires-Dist: GitPython
Provides-Extra: build
Requires-Dist: build ; extra == 'build'
Requires-Dist: twine ; extra == 'build'
